tiltpi/__init__.py
tiltpi/api.py
tiltpi/errors.py
tiltpi/model.py
tilt_pi-0.2.1.dist-info/LICENSE
tilt_pi-0.2.1.dist-info/METADATA
tilt_pi-0.2.1.dist-info/WHEEL
tilt_pi-0.2.1.dist-info/RECORD
