Metadata-Version: 2.3
Name: tilt-pi
Version: 0.2.1
Summary: A Python client for interacting with the Tilt Pi API
License: MIT
Keywords: tilt-pi,tilt,hydrometer,brewing,fermentation
Author: Michael Heyman
Author-email: michaelheyman@users.noreply.github.com
Requires-Python: >=3.13
Classifier: Development Status :: 4 - Beta
Classifier: Intended Audience :: Developers
Classifier: License :: OSI Approved :: MIT License
Classifier: Programming Language :: Python :: 3
Classifier: Programming Language :: Python :: 3.13
Classifier: Topic :: Software Development :: Libraries :: Python Modules
Classifier: Topic :: Home Automation
Classifier: Topic :: System :: Hardware
Classifier: Typing :: Typed
Requires-Dist: aiohttp (>=3.11.18,<4.0.0)
Project-URL: Repository, https://github.com/michaelheyman/tilt-pi
